contrary/__init__.py
contrary/contrary.py
contrary-0.1.dist-info/LICENSE.txt
contrary-0.1.dist-info/METADATA
contrary-0.1.dist-info/RECORD
contrary-0.1.dist-info/WHEEL
contrary-0.1.dist-info/top_level.txt
